plumbus/__init__.py
plumbus/__main__.py
plumbus/cli.py
plumbus/tests/test_example_tool.py
plumbus/tools/__init__.py
plumbus/tools/rabbitmq_shovel.py
plumbus/utils/logger.py
plumbus_cli-0.1.0.dist-info/METADATA
plumbus_cli-0.1.0.dist-info/WHEEL
plumbus_cli-0.1.0.dist-info/entry_points.txt
plumbus_cli-0.1.0.dist-info/top_level.txt
plumbus_cli-0.1.0.dist-info/RECORD
